voyllect/__init__.py
voyllect/aggregate.py
voyllect/collect.py
voyllect/driver.py
voyllect/init_dicts.py
voyllect/parser.py
voyllect/save.py
voyllect/transfer.py
voyllect/utils.py
voyllect-0.1.28.dist-info/METADATA
voyllect-0.1.28.dist-info/WHEEL
voyllect-0.1.28.dist-info/licenses/LICENSE
voyllect-0.1.28.dist-info/RECORD
