Metadata-Version: 2.4
Name: voyllect
Version: 0.1.28
Summary: Data aquisition package.
Project-URL: Homepage, https://github.com/Voysen/voyllect
Project-URL: Bug Tracker, https://github.com/Voysen/voyllect
Author-email: brenicolas <nicolas.breton@voysen.com>, OR98 <r.oumhmiz@gmail.com>
License-File: LICENSE
Classifier: License :: OSI Approved :: MIT License
Classifier: Operating System :: OS Independent
Classifier: Programming Language :: Python :: 3
Requires-Python: >=3.7
Requires-Dist: blinker==1.6
Requires-Dist: fake-useragent
Requires-Dist: selenium-wire
Requires-Dist: selenium==4.28.1
